ankr/__init__.py
ankr/advanced_apis.py
ankr/exceptions.py
ankr/providers.py
ankr/types.py
ankr/web3.py
ankr_sdk-1.0.3.dist-info/METADATA
ankr_sdk-1.0.3.dist-info/WHEEL
ankr_sdk-1.0.3.dist-info/licenses/LICENSE
ankr_sdk-1.0.3.dist-info/RECORD
