Metadata-Version: 2.4
Name: ankr-sdk
Version: 1.0.3
Summary: Compact Python library for interacting with Ankr's Advanced APIs.
License: MIT
License-File: LICENSE
Keywords: ankr,sdk,blockchain,nft
Author: Roman Fasakhov
Author-email: romanfasakhov@ankr.com
Requires-Python: >=3.8.1,<4.0.0
Classifier: License :: OSI Approved :: MIT License
Classifier: Programming Language :: Python :: 3
Classifier: Programming Language :: Python :: 3.9
Classifier: Programming Language :: Python :: 3.10
Classifier: Programming Language :: Python :: 3.11
Classifier: Programming Language :: Python :: 3.12
Classifier: Programming Language :: Python :: 3.13
Classifier: Programming Language :: Python :: 3.14
Requires-Dist: eth-typing (>=4.0.0,<5.0.0)
Requires-Dist: pydantic (>=2.0.8,<3.0.0)
Requires-Dist: pyhumps (>=3.8.0,<4.0.0)
Requires-Dist: typing-extensions (>=4.6.2,<5.0.0)
Requires-Dist: urllib3 (>=2.0.0,<3.0.0)
Requires-Dist: web3 (>=6.4.0,<7.0.0)
Project-URL: Homepage, https://ankr.com/
Project-URL: Repository, https://github.com/Ankr-network/ankr-python-sdk
